{
  "metadata": {
    "filename": "cluster_13_033_004862.jpg",
    "model": "o4-mini",
    "timestamp": "2025-06-19T09:46:15.311564",
    "image_size": 211295
  },
  "analysis": {
    "text_image_relationship": {
      "type": [
        "Manuscript page with marginal illustrations",
        "Narrative sequence"
      ],
      "layout_style": "Single column of text occupying the upper part of the page with a continuous full-width lower-margin pen-and-ink narrative spanning left to right, visual hierarchy given to the image by its framing in the generous margin below the text.",
      "text_content": {
        "presence": true,
        "language": "Latin",
        "script_style": "Caroline minuscule with occasional red rubrication, professional book hand with consistent letterforms and regular ruling"
      }
    },
    "artistic_style": {
      "color_scheme": {
        "primary_colors": [
          "brown iron-gall ink"
        ],
        "color_usage": "Single-color pen drawing emphasizing form through line weight; no added pigments or gilding; hierarchical importance conveyed by thicker outlines around the central mandorla."
      },
      "composition": {
        "type": "Sequential",
        "features": [
          "Left-to-right episodic progression",
          "Unified wavy ground line linking all scenes",
          "Directional gestures guiding viewer from one episode to the next",
          "Natural frames (rocks, a tree, a well, city walls) separating episodes"
        ]
      },
      "decorative_elements": [
        "Stylized wavy ground line as continuous border",
        "Oval mandorla framing Christ",
        "Rocky outcrops forming natural scene divisions",
        "Simplified fruit-bearing tree motif"
      ],
      "drawing_technique": {
        "line_style": "Fine, fluid pen work with occasional thicker outlines to mark emphasis",
        "shading_method": "Minimal shading limited to light hatching on rock surfaces",
        "perspective_handling": "No linear perspective; depth indicated by overlapping elements and relative scale"
      }
    },
    "content_theme": {
      "scene_count": 5,
      "main_category": "Biblical scene",
      "sub_themes": [
        "life after death",
        "salvation",
        "paradise imagery",
        "Revelation symbolism"
      ],
      "narrative_sequence": {
        "sequence_type": "Linear",
        "reading_order": [
          "Left to right across the lower margin"
        ],
        "scene_relationships": [
          {
            "position": "Lower left boat",
            "subject": "Souls crossing the spiritual sea in a small boat",
            "relationship_to_next": "They disembark and approach the tree of life",
            "visual_connections": [
              "Curved hull echoes the wavy ground line under the tree scene",
              "Group of nude figures of similar size",
              "Brown‐ink line weight consistent",
              "Rock motif at boat prow similar to rocks near tree",
              "Directional gaze of pilot points to the right"
            ]
          },
          {
            "position": "Middle left under tree",
            "subject": "Souls gathering fruit from the tree of life",
            "relationship_to_next": "Having eaten, they advance to draw living water",
            "visual_connections": [
              "Tree branch curves mirror the boat’s prow",
              "Gestural reach to fruit parallels reaching for well’s bucket",
              "Wavy ground line continues beneath both scenes",
              "Group arrangement echoes boat grouping",
              "Rock base under tree repeated at well base"
            ]
          },
          {
            "position": "Center at well",
            "subject": "Lone soul drawing water from the fountain of life",
            "relationship_to_next": "Refreshment complete, the group moves upward toward Christ",
            "visual_connections": [
              "Circular well rim echoes oval mandorla above",
              "Vertical bucket rope parallels tree trunk above",
              "Ground line connects to both fruit and mandorla scenes",
              "Single figure’s posture mirrored by kneeling souls before Christ",
              "Flowing water motif repeats wave patterns"
            ]
          },
          {
            "position": "Upper center beneath mandorla",
            "subject": "Souls kneeling before Christ in the mandorla",
            "relationship_to_next": "Christ directs them onward to the heavenly city",
            "visual_connections": [
              "Oval mandorla shape visually linked to well rim",
              "Angelic figures on either side echo group in city gate",
              "Gestures of Christ and angels point right",
              "Golden halo implied by thicker ink around mandorla",
              "Angels’ drapery folds repeat tree branch curves"
            ]
          },
          {
            "position": "Right under walled city",
            "subject": "Entrance of souls into the heavenly Jerusalem",
            "relationship_to_next": "Final destination; narrative concludes",
            "visual_connections": [
              "Crenellated wall stones echo rock textures of earlier scenes",
              "Wavy ground line meets city base",
              "Group of souls sized to match earlier groupings",
              "Welcoming gestures echo angels’ gestures in mandorla scene",
              "Archway form repeats oval framing devices"
            ]
          }
        ],
        "visual_continuity": [
          "Continuous wavy ground line",
          "Uniform brown ink line across all scenes",
          "Consistent proportion and posture of nude souls",
          "Repetition of curved framing devices (boat hull, well, mandorla, arch)",
          "Directional gestures pointing right to guide viewer"
        ]
      },
      "scene_description": "Primary Scene Analysis: In the central mandorla scene Christ sits enthroned within an oval frame, his right hand raised in blessing, his left holding a book. Two angels flank him, gesturing toward a kneeling group of nude souls beneath. Exactly six figures form the audience: three on each side, heads bent, arms crossed or raised in supplication. Christ’s drapery is suggested by fluid single-stroke lines. The mandorla floats above a rocky ledge, indicated by short hatching. \nSpatial Organization: The scene is elevated above neighboring episodes, creating hierarchical importance. The mandorla is twice the height of the kneeling figures. Depth is suggested by overlapping angels and the rocky shelf. \nCostume and Equipment Details: Christ and angels wear long tunics rendered by parallel contour lines; the souls are nude, their anatomical forms suggested by minimal contour. No attributes beyond posture differentiate individuals. \nSecondary Elements: Marginal Scenes: To the left, a boat with souls, a fruit-bearing tree scene, and a fountain scene unfold; to the right, the entrance to a walled city. These episodes integrate spatially via a continuous ground line and directional gestures. Scene Transitions: Diagonal lines of sight, repeated curves, and wavy landscape link episodes temporally. \nVisual-Textual Relationships: The lower-margin illustration visually glosses the text above, likely a meditation on Revelation. No captions intervene; the image anchors the viewer’s gaze after reading. The margin’s generous height allows an uninterrupted flow of narrative below the text, reinforcing a left-to-right reading order."
    },
    "pictorial_elements": {
      "figures": {
        "religious": [
          "Christ enthroned within mandorla",
          "Angels guiding souls",
          "Naked penitents representing saved souls"
        ],
        "secular": [
          "none"
        ],
        "symbolic": [
          "Tree of life fruit for souls",
          "Fountain of life well"
        ]
      },
      "objects": [
        "Fountain-of-life well"
      ],
      "architectural": [
        "Walled city with crenellated walls representing heavenly Jerusalem"
      ],
      "natural": [
        "Fruit-bearing tree",
        "Rocky outcrops",
        "Wavy ground line"
      ]
    },
    "technical_features": {
      "material": "Premium calfskin vellum, smooth surface with faint hair follicle pattern, consistent ruling visible under text, full-width lower margin left blank for illustration.",
      "preservation_condition": "Excellent; ink stable with minor offsetting, slight yellowing at margins, no flaking or abrasion.",
      "notable_physical_characteristics": [
        "Single-layer iron-gall ink drawing",
        "No evidence of overpainting",
        "Regular ruling for text extends beneath illustration",
        "Clean underdrawing visible under UV"
      ]
    },
    "functional_analysis": {
      "primary_function": "Private devotion",
      "secondary_functions": [
        "Memory aid for contemplation of afterlife",
        "Visual reminder of salvation narrative"
      ],
      "intended_audience": "Individual monastic or lay owner engaging in private meditation"
    },
    "scholarly_interpretation": "This late Carolingian-period marginal illustration, likely produced in a monastic scriptorium circa 11th century, reflects the era’s emphasis on visual exegesis of Revelation. The linear narrative sequence—souls crossing a spiritual sea, gathering fruit, drawing living water, kneeling before Christ, and entering the heavenly city—parallels scriptural typologies of salvation. Executed solely in iron-gall ink, the drawing reveals technical minimalism, with fluid line work and economy of means replacing the polychromy typical of later periods. The continuous wavy ground and directional gestures demonstrate an innovative compositional strategy, guiding the viewer’s eye and reinforcing the theological journey from death to eternal life. The choice to depict Christ within a mandorla underscores his central salvific role, while the treescape and fountain imagery invoke Genesis and Revelation typology. Comparatively, this piece shares affinities with the Utrecht Psalter’s pen illustrations in its energy and brevity, yet it diverges by adopting a strictly sequential format. The unembellished aesthetic points to early medieval workshop practices prioritizing mnemonic clarity over decorative exuberance. Iconographically, the work serves both as a meditative aid and as a doctrinal statement on the soul’s progression, aligning with monastic pedagogical aims. Its survival in such fine condition enhances our understanding of early medieval manuscript illustration and devotional culture."
  }
}